pyfeasst/__init__.py
pyfeasst/accumulator.py
pyfeasst/cd.py
pyfeasst/coarse_grain_pdb.py
pyfeasst/fstio.py
pyfeasst/fstplot.py
pyfeasst/macrostate_distribution.py
pyfeasst/multistate_accumulator.py
pyfeasst/physical_constants.py
pyfeasst/scattering.py
pyfeasst-0.0.3.dist-info/LICENSE
pyfeasst-0.0.3.dist-info/METADATA
pyfeasst-0.0.3.dist-info/WHEEL
pyfeasst-0.0.3.dist-info/top_level.txt
pyfeasst-0.0.3.dist-info/RECORD
