Metadata-Version: 2.1
Name: pyfeasst
Version: 0.0.3
Summary: A Python package to analyze FEASST simulation results.
Home-page: https://doi.org/10.18434/M3S095
Author: Harold Wickes Hatch
Author-email: harold.hatch@nist.gov
Classifier: Programming Language :: Python :: 3
Classifier: Operating System :: OS Independent
Requires-Python: >=3.6
License-File: LICENSE
